ipulse_shared_data_eng_ftredge/__init__.py
ipulse_shared_data_eng_ftredge/cloud_level_one/__init__.py
ipulse_shared_data_eng_ftredge/cloud_level_one/cloud_common.py
ipulse_shared_data_eng_ftredge/cloud_level_one/cloud_gcp_bigquery.py
ipulse_shared_data_eng_ftredge/cloud_level_one/cloud_gcp_firestore.py
ipulse_shared_data_eng_ftredge/cloud_level_one/cloud_gcp_pubsub.py
ipulse_shared_data_eng_ftredge/cloud_level_one/cloud_gcp_secrets.py
ipulse_shared_data_eng_ftredge/cloud_level_one/cloud_gcp_storage.py
ipulse_shared_data_eng_ftredge/cloud_level_two/__init__.py
ipulse_shared_data_eng_ftredge/cloud_level_two/cloud_gcp_bigquery_controlled_changes.py
ipulse_shared_data_eng_ftredge/domain_etl/__init__.py
ipulse_shared_data_eng_ftredge/domain_etl/fincore/__init__.py
ipulse_shared_data_eng_ftredge/domain_etl/fincore/market/__init__.py
ipulse_shared_data_eng_ftredge/domain_etl/fincore/market/formatting.py
ipulse_shared_data_eng_ftredge/domain_etl/fincore/market/get_attributes.py
ipulse_shared_data_eng_ftredge/domain_etl/fincore/market/market_records_mapping.py
ipulse_shared_data_eng_ftredge/domain_etl/fincore/market/preprocessing.py
ipulse_shared_data_eng_ftredge/domain_etl/fincore/market/sourcing_corporate_actions_from_api.py
ipulse_shared_data_eng_ftredge/domain_etl/fincore/market/sourcing_ohcva_from_api.py
ipulse_shared_data_eng_ftredge/etl_runtime/__init__.py
ipulse_shared_data_eng_ftredge/etl_runtime/etl_runtime_tracker.py
ipulse_shared_data_eng_ftredge/local_level_one/__init__.py
ipulse_shared_data_eng_ftredge/local_level_one/local_read_writes.py
ipulse_shared_data_eng_ftredge/pipelines/__init__.py
ipulse_shared_data_eng_ftredge/pipelines/dependency.py
ipulse_shared_data_eng_ftredge/pipelines/function_result.py
ipulse_shared_data_eng_ftredge/pipelines/pipe_and_ops_exceptions.py
ipulse_shared_data_eng_ftredge/pipelines/pipeline_memory.py
ipulse_shared_data_eng_ftredge/pipelines/pipelineflow.py
ipulse_shared_data_eng_ftredge/pipelines/pipelineflow_helpers.py
ipulse_shared_data_eng_ftredge-12.9.0.dist-info/licenses/LICENCE
ipulse_shared_data_eng_ftredge-12.9.0.dist-info/METADATA
ipulse_shared_data_eng_ftredge-12.9.0.dist-info/WHEEL
ipulse_shared_data_eng_ftredge-12.9.0.dist-info/top_level.txt
ipulse_shared_data_eng_ftredge-12.9.0.dist-info/RECORD
