Metadata-Version: 2.4
Name: ipulse-shared-data-eng-ftredge
Version: 12.9.0
Summary: Shared Data Engineering functions for the Pulse platform project. Using AI for financial advisory and investment management.
Home-page: https://github.com/TheFutureEdge/ipulse_shared_data_eng
Author: Russlan Ramdowar
License-File: LICENCE
Requires-Dist: ipulse_shared_base_ftredge~=12.11.0
Requires-Dist: python-dateutil~=2.9.0
Requires-Dist: pydantic~=2.12.5
Requires-Dist: google-cloud-bigquery~=3.40.0
Requires-Dist: google-cloud-storage~=3.8.0
Requires-Dist: google-cloud-pubsub~=2.34.0
Requires-Dist: google-cloud-secret-manager~=2.26.0
Requires-Dist: google-cloud-firestore~=2.23.0
Dynamic: author
Dynamic: home-page
Dynamic: license-file
Dynamic: requires-dist
Dynamic: summary
